{
    "age": 3,
    "characters": [
        {
            "character": 72,
            "points": [
                {
                    "x": 0.12686567164179105,
                    "y": 0.0
                },
                {
                    "x": 0.12686567164179105,
                    "y": 0.005714285714285714
                },
                {
                    "x": 0.12686567164179105,
                    "y": 0.011428571428571429
                },
                {
                    "x": 0.12686567164179105,
                    "y": 0.05142857142857143
                },
                {
                    "x": 0.12686567164179105,
                    "y": 0.08
                },
                {
                    "x": 0.1044776119402985,
                    "y": 0.13714285714285715
                },
                {
                    "x": 0.09701492537313433,
                    "y": 0.18857142857142858
                },
                {
                    "x": 0.08955223880597014,
                    "y": 0.2571428571428571
                },
                {
                    "x": 0.06716417910447761,
                    "y": 0.34285714285714286
                },
                {
                    "x": 0.05223880597014925,
                    "y": 0.41714285714285715
                },
                {
                    "x": 0.04477611940298507,
                    "y": 0.5028571428571429
                },
                {
                    "x": 0.029850746268656716,
                    "y": 0.6057142857142858
                },
                {
                    "x": 0.022388059701492536,
                    "y": 0.6628571428571428
                },
                {
                    "x": 0.007462686567164179,
                    "y": 0.76
                },
                {
                    "x": 0.007462686567164179,
                    "y": 0.8171428571428572
                },
                {
                    "x": 0.007462686567164179,
                    "y": 0.8685714285714285
                },
                {
                    "x": 0.007462686567164179,
                    "y": 0.8971428571428571
                },
                {
                    "x": 0.007462686567164179,
                    "y": 0.9257142857142857
                },
                {
                    "x": 0.007462686567164179,
                    "y": 0.9714285714285714
                },
                {
                    "x": 0.007462686567164179,
                    "y": 0.9828571428571429
                },
                {
                    "x": 0.014925373134328358,
                    "y": 1.0
                },
                {
                    "x": -2.7761194029850746,
                    "y": -0.9714285714285714
                },
                {
                    "x": 0.6716417910447762,
                    "y": 0.17714285714285713
                },
                {
                    "x": 0.6716417910447762,
                    "y": 0.18857142857142858
                },
                {
                    "x": 0.6716417910447762,
                    "y": 0.2
                },
                {
                    "x": 0.6716417910447762,
                    "y": 0.21714285714285714
                },
                {
                    "x": 0.664179104477612,
                    "y": 0.2571428571428571
                },
                {
                    "x": 0.6567164179104478,
                    "y": 0.28
                },
                {
                    "x": 0.6492537313432836,
                    "y": 0.33714285714285713
                },
                {
                    "x": 0.6417910447761194,
                    "y": 0.4057142857142857
                },
                {
                    "x": 0.6343283582089553,
                    "y": 0.49714285714285716
                },
                {
                    "x": 0.6268656716417911,
                    "y": 0.5542857142857143
                },
                {
                    "x": 0.6194029850746269,
                    "y": 0.6228571428571429
                },
                {
                    "x": 0.6044776119402985,
                    "y": 0.7257142857142858
                },
                {
                    "x": 0.5970149253731343,
                    "y": 0.7885714285714286
                },
                {
                    "x": 0.5895522388059702,
                    "y": 0.8457142857142858
                },
                {
                    "x": 0.5671641791044776,
                    "y": 0.92
                },
                {
                    "x": 0.5671641791044776,
                    "y": 0.9485714285714286
                },
                {
                    "x": 0.5671641791044776,
                    "y": 0.9657142857142857
                },
                {
                    "x": 0.5597014925373134,
                    "y": 0.9714285714285714
                },
                {
                    "x": -2.7761194029850746,
                    "y": -0.9714285714285714
                },
                {
                    "x": 0.0,
                    "y": 0.5257142857142857
                },
                {
                    "x": 0.007462686567164179,
                    "y": 0.5257142857142857
                },
                {
                    "x": 0.014925373134328358,
                    "y": 0.5257142857142857
                },
                {
                    "x": 0.05223880597014925,
                    "y": 0.52
                },
                {
                    "x": 0.1044776119402985,
                    "y": 0.52
                },
                {
                    "x": 0.1791044776119403,
                    "y": 0.52
                },
                {
                    "x": 0.27611940298507465,
                    "y": 0.52
                },
                {
                    "x": 0.41044776119402987,
                    "y": 0.52
                },
                {
                    "x": 0.5074626865671642,
                    "y": 0.52
                },
                {
                    "x": 0.6194029850746269,
                    "y": 0.52
                },
                {
                    "x": 0.7164179104477612,
                    "y": 0.5257142857142857
                },
                {
                    "x": 0.8134328358208955,
                    "y": 0.5257142857142857
                },
                {
                    "x": 0.8731343283582089,
                    "y": 0.5257142857142857
                },
                {
                    "x": 0.9402985074626866,
                    "y": 0.5257142857142857
                },
                {
                    "x": 0.9925373134328358,
                    "y": 0.5257142857142857
                },
                {
                    "x": 1.0,
                    "y": 0.5257142857142857
                },
                {
                    "x": -2.7761194029850746,
                    "y": -0.9714285714285714
                }
            ]
        },
        {
            "character": 87,
            "points": [
                {
                    "x": 0.005714285714285714,
                    "y": 0.006211180124223602
                },
                {
                    "x": -2.177142857142857,
                    "y": -0.9813664596273292
                },
                {
                    "x": 0.0,
                    "y": 0.0
                },
                {
                    "x": 0.0,
                    "y": 0.006211180124223602
                },
                {
                    "x": 0.0,
                    "y": 0.043478260869565216
                },
                {
                    "x": 0.005714285714285714,
                    "y": 0.07453416149068323
                },
                {
                    "x": 0.017142857142857144,
                    "y": 0.11180124223602485
                },
                {
                    "x": 0.022857142857142857,
                    "y": 0.16149068322981366
                },
                {
                    "x": 0.045714285714285714,
                    "y": 0.2236024844720497
                },
                {
                    "x": 0.06285714285714286,
                    "y": 0.3105590062111801
                },
                {
                    "x": 0.09142857142857143,
                    "y": 0.40372670807453415
                },
                {
                    "x": 0.11428571428571428,
                    "y": 0.45962732919254656
                },
                {
                    "x": 0.14857142857142858,
                    "y": 0.5590062111801242
                },
                {
                    "x": 0.17142857142857143,
                    "y": 0.6149068322981367
                },
                {
                    "x": 0.18857142857142858,
                    "y": 0.6645962732919255
                },
                {
                    "x": 0.21714285714285714,
                    "y": 0.7453416149068323
                },
                {
                    "x": 0.2342857142857143,
                    "y": 0.7950310559006211
                },
                {
                    "x": 0.25142857142857145,
                    "y": 0.8385093167701864
                },
                {
                    "x": 0.26285714285714284,
                    "y": 0.8757763975155279
                },
                {
                    "x": 0.26857142857142857,
                    "y": 0.906832298136646
                },
                {
                    "x": 0.2742857142857143,
                    "y": 0.9316770186335404
                },
                {
                    "x": 0.2742857142857143,
                    "y": 0.9565217391304348
                },
                {
                    "x": 0.28,
                    "y": 0.968944099378882
                },
                {
                    "x": 0.28,
                    "y": 0.9875776397515528
                },
                {
                    "x": 0.28,
                    "y": 0.9937888198757764
                },
                {
                    "x": 0.2857142857142857,
                    "y": 0.9937888198757764
                },
                {
                    "x": 0.29714285714285715,
                    "y": 0.9192546583850931
                },
                {
                    "x": 0.30857142857142855,
                    "y": 0.84472049689441
                },
                {
                    "x": 0.32571428571428573,
                    "y": 0.7018633540372671
                },
                {
                    "x": 0.3314285714285714,
                    "y": 0.6024844720496895
                },
                {
                    "x": 0.36,
                    "y": 0.45962732919254656
                },
                {
                    "x": 0.37142857142857144,
                    "y": 0.36645962732919257
                },
                {
                    "x": 0.3942857142857143,
                    "y": 0.2732919254658385
                },
                {
                    "x": 0.4057142857142857,
                    "y": 0.21739130434782608
                },
                {
                    "x": 0.41714285714285715,
                    "y": 0.18633540372670807
                },
                {
                    "x": 0.42857142857142855,
                    "y": 0.14906832298136646
                },
                {
                    "x": 0.44,
                    "y": 0.12422360248447205
                },
                {
                    "x": 0.44571428571428573,
                    "y": 0.10559006211180125
                },
                {
                    "x": 0.4514285714285714,
                    "y": 0.08695652173913043
                },
                {
                    "x": 0.45714285714285713,
                    "y": 0.08074534161490683
                },
                {
                    "x": 0.45714285714285713,
                    "y": 0.08695652173913043
                },
                {
                    "x": 0.4685714285714286,
                    "y": 0.14285714285714285
                },
                {
                    "x": 0.4857142857142857,
                    "y": 0.2111801242236025
                },
                {
                    "x": 0.49714285714285716,
                    "y": 0.2981366459627329
                },
                {
                    "x": 0.52,
                    "y": 0.391304347826087
                },
                {
                    "x": 0.5428571428571428,
                    "y": 0.4968944099378882
                },
                {
                    "x": 0.5771428571428572,
                    "y": 0.6645962732919255
                },
                {
                    "x": 0.6114285714285714,
                    "y": 0.7950310559006211
                },
                {
                    "x": 0.64,
                    "y": 0.8695652173913043
                },
                {
                    "x": 0.6685714285714286,
                    "y": 0.9254658385093167
                },
                {
                    "x": 0.6857142857142857,
                    "y": 0.968944099378882
                },
                {
                    "x": 0.7028571428571428,
                    "y": 0.9937888198757764
                },
                {
                    "x": 0.7142857142857143,
                    "y": 1.0
                },
                {
                    "x": 0.72,
                    "y": 0.9875776397515528
                },
                {
                    "x": 0.7314285714285714,
                    "y": 0.9192546583850931
                },
                {
                    "x": 0.7371428571428571,
                    "y": 0.8385093167701864
                },
                {
                    "x": 0.76,
                    "y": 0.7453416149068323
                },
                {
                    "x": 0.7828571428571428,
                    "y": 0.6149068322981367
                },
                {
                    "x": 0.8057142857142857,
                    "y": 0.5217391304347826
                },
                {
                    "x": 0.8342857142857143,
                    "y": 0.453416149068323
                },
                {
                    "x": 0.8685714285714285,
                    "y": 0.36645962732919257
                },
                {
                    "x": 0.8914285714285715,
                    "y": 0.3167701863354037
                },
                {
                    "x": 0.9257142857142857,
                    "y": 0.2670807453416149
                },
                {
                    "x": 0.96,
                    "y": 0.21739130434782608
                },
                {
                    "x": 0.9771428571428571,
                    "y": 0.19254658385093168
                },
                {
                    "x": 1.0,
                    "y": 0.16149068322981366
                },
                {
                    "x": -2.177142857142857,
                    "y": -0.9813664596273292
                }
            ]
        },
        {
            "character": 70,
            "points": [
                {
                    "x": 0.03496503496503497,
                    "y": 0.08771929824561403
                },
                {
                    "x": 0.03496503496503497,
                    "y": 0.11695906432748537
                },
                {
                    "x": 0.04195804195804196,
                    "y": 0.15789473684210525
                },
                {
                    "x": 0.04895104895104895,
                    "y": 0.21052631578947367
                },
                {
                    "x": 0.04895104895104895,
                    "y": 0.2573099415204678
                },
                {
                    "x": 0.06293706293706294,
                    "y": 0.3391812865497076
                },
                {
                    "x": 0.07692307692307693,
                    "y": 0.4093567251461988
                },
                {
                    "x": 0.08391608391608392,
                    "y": 0.47953216374269003
                },
                {
                    "x": 0.08391608391608392,
                    "y": 0.5555555555555556
                },
                {
                    "x": 0.09090909090909091,
                    "y": 0.6081871345029239
                },
                {
                    "x": 0.09090909090909091,
                    "y": 0.695906432748538
                },
                {
                    "x": 0.09090909090909091,
                    "y": 0.7719298245614035
                },
                {
                    "x": 0.08391608391608392,
                    "y": 0.8245614035087719
                },
                {
                    "x": 0.07692307692307693,
                    "y": 0.8713450292397661
                },
                {
                    "x": 0.06293706293706294,
                    "y": 0.9239766081871345
                },
                {
                    "x": 0.06293706293706294,
                    "y": 0.9532163742690059
                },
                {
                    "x": 0.06293706293706294,
                    "y": 0.9766081871345029
                },
                {
                    "x": 0.06293706293706294,
                    "y": 0.9883040935672515
                },
                {
                    "x": 0.055944055944055944,
                    "y": 1.0
                },
                {
                    "x": 0.055944055944055944,
                    "y": 0.9941520467836257
                },
                {
                    "x": 0.055944055944055944,
                    "y": 0.9649122807017544
                },
                {
                    "x": 0.04895104895104895,
                    "y": 0.9298245614035088
                },
                {
                    "x": 0.04195804195804196,
                    "y": 0.8713450292397661
                },
                {
                    "x": 0.03496503496503497,
                    "y": 0.8245614035087719
                },
                {
                    "x": 0.03496503496503497,
                    "y": 0.7660818713450293
                },
                {
                    "x": 0.02097902097902098,
                    "y": 0.7192982456140351
                },
                {
                    "x": 0.02097902097902098,
                    "y": 0.6549707602339181
                },
                {
                    "x": 0.02097902097902098,
                    "y": 0.6023391812865497
                },
                {
                    "x": 0.013986013986013986,
                    "y": 0.5380116959064327
                },
                {
                    "x": 0.013986013986013986,
                    "y": 0.47953216374269003
                },
                {
                    "x": 0.006993006993006993,
                    "y": 0.42105263157894735
                },
                {
                    "x": 0.006993006993006993,
                    "y": 0.38596491228070173
                },
                {
                    "x": 0.006993006993006993,
                    "y": 0.3391812865497076
                },
                {
                    "x": 0.006993006993006993,
                    "y": 0.3216374269005848
                },
                {
                    "x": 0.006993006993006993,
                    "y": 0.28654970760233917
                },
                {
                    "x": 0.006993006993006993,
                    "y": 0.26900584795321636
                },
                {
                    "x": 0.006993006993006993,
                    "y": 0.2573099415204678
                },
                {
                    "x": 0.006993006993006993,
                    "y": 0.23976608187134502
                },
                {
                    "x": 0.006993006993006993,
                    "y": 0.21637426900584794
                },
                {
                    "x": 0.006993006993006993,
                    "y": 0.2046783625730994
                },
                {
                    "x": 0.006993006993006993,
                    "y": 0.19298245614035087
                },
                {
                    "x": 0.0,
                    "y": 0.1695906432748538
                },
                {
                    "x": 0.0,
                    "y": 0.15789473684210525
                },
                {
                    "x": 0.0,
                    "y": 0.14035087719298245
                },
                {
                    "x": 0.0,
                    "y": 0.12280701754385964
                },
                {
                    "x": 0.0,
                    "y": 0.1111111111111111
                },
                {
                    "x": 0.0,
                    "y": 0.09941520467836257
                },
                {
                    "x": 0.0,
                    "y": 0.0935672514619883
                },
                {
                    "x": 0.0,
                    "y": 0.08771929824561403
                },
                {
                    "x": 0.0,
                    "y": 0.08187134502923976
                },
                {
                    "x": 0.0,
                    "y": 0.06432748538011696
                },
                {
                    "x": 0.0,
                    "y": 0.05847953216374269
                },
                {
                    "x": 0.006993006993006993,
                    "y": 0.04678362573099415
                },
                {
                    "x": 0.013986013986013986,
                    "y": 0.04093567251461988
                },
                {
                    "x": 0.013986013986013986,
                    "y": 0.029239766081871343
                },
                {
                    "x": 0.013986013986013986,
                    "y": 0.023391812865497075
                },
                {
                    "x": 0.02097902097902098,
                    "y": 0.017543859649122806
                },
                {
                    "x": 0.02097902097902098,
                    "y": 0.011695906432748537
                },
                {
                    "x": 0.02097902097902098,
                    "y": 0.0
                },
                {
                    "x": 0.027972027972027972,
                    "y": 0.0
                },
                {
                    "x": 0.03496503496503497,
                    "y": 0.0
                },
                {
                    "x": 0.055944055944055944,
                    "y": 0.0
                },
                {
                    "x": 0.07692307692307693,
                    "y": 0.0
                },
                {
                    "x": 0.0979020979020979,
                    "y": 0.0
                },
                {
                    "x": 0.11888111888111888,
                    "y": 0.0
                },
                {
                    "x": 0.14685314685314685,
                    "y": 0.0
                },
                {
                    "x": 0.16083916083916083,
                    "y": 0.0
                },
                {
                    "x": 0.1888111888111888,
                    "y": 0.0
                },
                {
                    "x": 0.20279720279720279,
                    "y": 0.005847953216374269
                },
                {
                    "x": 0.22377622377622378,
                    "y": 0.005847953216374269
                },
                {
                    "x": 0.23776223776223776,
                    "y": 0.005847953216374269
                },
                {
                    "x": 0.24475524475524477,
                    "y": 0.011695906432748537
                },
                {
                    "x": 0.25874125874125875,
                    "y": 0.011695906432748537
                },
                {
                    "x": 0.2727272727272727,
                    "y": 0.011695906432748537
                },
                {
                    "x": 0.2867132867132867,
                    "y": 0.011695906432748537
                },
                {
                    "x": 0.3006993006993007,
                    "y": 0.011695906432748537
                },
                {
                    "x": 0.3076923076923077,
                    "y": 0.011695906432748537
                },
                {
                    "x": 0.32867132867132864,
                    "y": 0.011695906432748537
                },
                {
                    "x": 0.3356643356643357,
                    "y": 0.011695906432748537
                },
                {
                    "x": -2.7552447552447554,
                    "y": -0.9824561403508771
                },
                {
                    "x": 0.013986013986013986,
                    "y": 0.4444444444444444
                },
                {
                    "x": 0.013986013986013986,
                    "y": 0.4502923976608187
                },
                {
                    "x": 0.027972027972027972,
                    "y": 0.4502923976608187
                },
                {
                    "x": 0.04895104895104895,
                    "y": 0.4502923976608187
                },
                {
                    "x": 0.06293706293706294,
                    "y": 0.4502923976608187
                },
                {
                    "x": 0.13986013986013987,
                    "y": 0.43859649122807015
                },
                {
                    "x": 0.20279720279720279,
                    "y": 0.4327485380116959
                },
                {
                    "x": 0.2867132867132867,
                    "y": 0.42105263157894735
                },
                {
                    "x": 0.3776223776223776,
                    "y": 0.4093567251461988
                },
                {
                    "x": 0.46853146853146854,
                    "y": 0.40350877192982454
                },
                {
                    "x": 0.5734265734265734,
                    "y": 0.39766081871345027
                },
                {
                    "x": 0.6853146853146853,
                    "y": 0.38011695906432746
                },
                {
                    "x": 0.7902097902097902,
                    "y": 0.3742690058479532
                },
                {
                    "x": 0.8531468531468531,
                    "y": 0.36257309941520466
                },
                {
                    "x": 0.9440559440559441,
                    "y": 0.34502923976608185
                },
                {
                    "x": 1.0,
                    "y": 0.3391812865497076
                },
                {
                    "x": -2.7552447552447554,
                    "y": -0.9824561403508771
                }
            ]
        }
    ],
    "gender": 0,
    "hand": 0,
    "name": [
        97,
        115,
        107,
        97
    ]
}